yamlforge/__init__.py
yamlforge/main.py
yamlforge/parser.py
yamlforge/utils.py
yamlforge-0.1.2.dist-info/METADATA
yamlforge-0.1.2.dist-info/WHEEL
yamlforge-0.1.2.dist-info/top_level.txt
yamlforge-0.1.2.dist-info/RECORD
