Metadata-Version: 2.2
Name: yamlforge
Version: 0.1.2
Summary: YAMLForge is a library designed to automatically generate SQLModel models and shcemas from a configuration in YAML format or a dictionary.
Author-email: Sebastian Sala <sebastian.sala.alanis@hotmail.com>
Project-URL: Homepage, https://github.com/sebas-sala/yamlforge
Project-URL: Bug Tracker, https://github.com/sebas-sala/yamlforge/issues
Requires-Python: >=3.12
Requires-Dist: inflect>=7.5.0
Requires-Dist: pyyaml>=6.0.2
Requires-Dist: sqlmodel>=0.0.22
